ASQRT/rtl/sqrtiu.v
/*
    SQRT Iteration Unit
    This unit makes a single attempt at iterating the square root.
    This works like the contents of the 'while' loop inside src/algo.js.
    
    SQRTIUs operate combinationally and thus can be chained together and controlled by a clocked dispatcher.
    This allows a choice between large/single-cycle, compact/variable-cycle, or a balance. 
	It is also possible to use fewer cycles by starting at the MSB of the argument.
	Alternatively, it is may be possible to operate with an "epsilon threshold" that reduces cycle count by lowering precision.

    An SQRTIU takes the attempted value of the previous iteration, the epsilon of the previous iteration, and the result of the previous iteration.
    It outputs the same information but for the current iteration.
*/

module anfsqrt_sqrtiu (
    input [31:0] prev_att,
    input [31:0] prev_eps,
    input [31:0] prev_res,

    output [31:0] this_att,
    output [31:0] this_eps,
    output [31:0] this_res
);

    assign this_att = {1'b0, prev_att[31:1]};

	wire [31:0] this_delta_term1_half;
	wire [31:0] this_delta;
	reg [4:0] this_att_msb;
	wire [31:0] this_att_sq_exp;
	wire [31:0] this_att_sq;

    assign this_att_sq_exp = {this_att_msb, 1'b0};
    assign this_att_sq = 32'b1 << this_att_sq_exp;

	assign this_delta_term1_half = prev_res << this_att_msb;
	assign this_delta = {this_delta_term1_half[30:0], 1'b0} + this_att_sq;

	wire cond_met;
	assign cond_met = this_delta <= prev_eps;
	assign this_eps = cond_met ? prev_eps - this_delta : prev_eps; 
	assign this_res = cond_met ? prev_res | this_att : prev_res; 

    integer msb_idx;
    always @* begin
        this_att_msb = 0;

        for (msb_idx=0; msb_idx<32; msb_idx++) begin
			if(this_att == (1 << msb_idx)) this_att_msb = msb_idx[4:0];
        end
    end

endmodule

ASQRT/rtl/sqrtiu_tb.v
`include "sqrtiu.v"
`timescale 1ns/1ns

module anfsqrt_sqrtiu_tb();
    reg clk;
    reg [31:0] cyc;

    reg [31:0] prev_att;
    reg [31:0] prev_eps;
    reg [31:0] prev_res;

    wire [31:0] this_att;
    wire [31:0] this_eps;
    wire [31:0] this_res;

    anfsqrt_sqrtiu DUT (prev_att, prev_eps, prev_res, this_att, this_eps, this_res);

    always @(posedge clk) begin
        $display("Cycle", cyc, " Attempting:", this_att, " Epsilon: ", this_eps, " Current Result:", this_res);
        prev_att <= this_att;
        prev_eps <= this_eps;
        prev_res <= this_res;
        cyc <= cyc + 1;
    end

    initial begin
        $dumpfile("sqrtiu_tb.vcd");
        $dumpvars;  

        prev_att = 1 << 16;
        prev_eps = 256;
        prev_res = 0;
        clk = 0;
        cyc = 0;

        repeat (64) begin
        #1 clk = !clk;
        end
    end

endmodule

ASQRT/rtl/sqrtiu_tb.vcd
$date
	Thu Feb 17 22:03:58 2022
$end
$version
	Icarus Verilog
$end
$timescale
	1ns
$end
$scope module anfsqrt_sqrtiu_tb $end
$var wire 32 ! this_res [31:0] $end
$var wire 32 " this_eps [31:0] $end
$var wire 32 # this_att [31:0] $end
$var reg 1 $ clk $end
$var reg 32 % cyc [31:0] $end
$var reg 32 & prev_att [31:0] $end
$var reg 32 ' prev_eps [31:0] $end
$var reg 32 ( prev_res [31:0] $end
$scope module DUT $end
$var wire 32 ) prev_att [31:0] $end
$var wire 32 * prev_eps [31:0] $end
$var wire 32 + prev_res [31:0] $end
$var wire 32 , this_res [31:0] $end
$var wire 32 - this_eps [31:0] $end
$var wire 32 . this_delta_term1_half [31:0] $end
$var wire 32 / this_delta [31:0] $end
$var wire 32 0 this_att_sq_exp [31:0] $end
$var wire 32 1 this_att_sq [31:0] $end
$var wire 32 2 this_att [31:0] $end
$var wire 1 3 cond_met $end
$var reg 5 4 this_att_msb [4:0] $end
$var integer 32 5 msb_idx [31:0] $end
$upscope $end
$upscope $end
$enddefinitions $end
#0
$dumpvars
b100000 5
b1111 4
03
b1000000000000000 2
b1000000000000000000000000000000 1
b11110 0
b1000000000000000000000000000000 /
b0 .
b100000000 -
b0 ,
b0 +
b100000000 *
b10000000000000000 )
b0 (
b100000000 '
b10000000000000000 &
b0 %
0$
b1000000000000000 #
b100000000 "
b0 !
$end
#1
b100000 5
03
b10000000000000000000000000000 /
b10000000000000000000000000000 1
b11100 0
b1110 4
b100000000000000 #
b100000000000000 2
b1 %
b1000000000000000 &
b1000000000000000 )
1$
#2
0$
#3
b100000 5
03
b100000000000000000000000000 /
b100000000000000000000000000 1
b11010 0
b1101 4
b10000000000000 #
b10000000000000 2
b10 %
b100000000000000 &
b100000000000000 )
1$
#4
0$
#5
b100000 5
03
b1000000000000000000000000 /
b1000000000000000000000000 1
b11000 0
b1100 4
b1000000000000 #
b1000000000000 2
b11 %
b10000000000000 &
b10000000000000 )
1$
#6
0$
#7
b100000 5
03
b10000000000000000000000 /
b10000000000000000000000 1
b10110 0
b1011 4
b100000000000 #
b100000000000 2
b100 %
b1000000000000 &
b1000000000000 )
1$
#8
0$
#9
b100000 5
03
b100000000000000000000 /
b100000000000000000000 1
b10100 0
b1010 4
b10000000000 #
b10000000000 2
b101 %
b100000000000 &
b100000000000 )
1$
#10
0$
#11
b100000 5
03
b1000000000000000000 /
b1000000000000000000 1
b10010 0
b1001 4
b1000000000 #
b1000000000 2
b110 %
b10000000000 &
b10000000000 )
1$
#12
0$
#13
b100000 5
03
b10000000000000000 /
b10000000000000000 1
b10000 0
b1000 4
b100000000 #
b100000000 2
b111 %
b1000000000 &
b1000000000 )
1$
#14
0$
#15
b100000 5
03
b100000000000000 /
b100000000000000 1
b1110 0
b111 4
b10000000 #
b10000000 2
b1000 %
b100000000 &
b100000000 )
1$
#16
0$
#17
b100000 5
03
b1000000000000 /
b1000000000000 1
b1100 0
b110 4
b1000000 #
b1000000 2
b1001 %
b10000000 &
b10000000 )
1$
#18
0$
#19
b100000 5
03
b10000000000 /
b10000000000 1
b1010 0
b101 4
b100000 #
b100000 2
b1010 %
b1000000 &
b1000000 )
1$
#20
0$
#21
b0 "
b0 -
b10000 !
b10000 ,
b100000 5
13
b100000000 /
b100000000 1
b1000 0
b100 4
b10000 #
b10000 2
b1011 %
b100000 &
b100000 )
1$
#22
0$
#23
b100000 5
b1000000 1
b110 0
b11 4
b101000000 /
b1000 #
b1000 2
b1100 %
b10000000 .
b10000 (
b10000 +
03
b0 '
b0 *
b10000 &
b10000 )
1$
#24
0$
#25
b100000 5
b10010000 /
b10000 1
b100 0
b1000000 .
b10 4
b100 #
b100 2
b1101 %
b1000 &
b1000 )
1$
#26
0$
#27
b100000 5
b1000100 /
b100 1
b10 0
b100000 .
b1 4
b10 #
b10 2
b1110 %
b100 &
b100 )
1$
#28
0$
#29
b100000 5
b100001 /
b1 1
b0 0
b10000 .
b0 4
b1 #
b1 2
b1111 %
b10 &
b10 )
1$
#30
0$
#31
b100000 5
b0 #
b0 2
b10000 %
b1 &
b1 )
1$
#32
0$
#33
b10001 %
b0 &
b0 )
1$
#34
0$
#35
b10010 %
1$
#36
0$
#37
b10011 %
1$
#38
0$
#39
b10100 %
1$
#40
0$
#41
b10101 %
1$
#42
0$
#43
b10110 %
1$
#44
0$
#45
b10111 %
1$
#46
0$
#47
b11000 %
1$
#48
0$
#49
b11001 %
1$
#50
0$
#51
b11010 %
1$
#52
0$
#53
b11011 %
1$
#54
0$
#55
b11100 %
1$
#56
0$
#57
b11101 %
1$
#58
0$
#59
b11110 %
1$
#60
0$
#61
b11111 %
1$
#62
0$
#63
b100000 %
1$
